setup.py
sdcadmin/__init__.py
sdcadmin/datacenter.py
sdcadmin/job.py
sdcadmin/machine.py
sdcadmin/network.py
sdcadmin/package.py
sdcadmin.egg-info/PKG-INFO
sdcadmin.egg-info/SOURCES.txt
sdcadmin.egg-info/dependency_links.txt
sdcadmin.egg-info/pbr.json
sdcadmin.egg-info/requires.txt
sdcadmin.egg-info/top_level.txt
sdcadmin/tests/__init__.py
sdcadmin/tests/functional.py
sdcadmin/tests/test_datacenter.py
sdcadmin/tests/test_job.py
sdcadmin/tests/test_machine.py
sdcadmin/tests/test_network.py
sdcadmin/tests/test_network_lifecycle.py
sdcadmin/tests/test_package.py
sdcadmin/tests/test_vm_lifecycle.py
sdcadmin/tests/test_vm_networks_lifecycle.py
sdcadmin/tests/config/__init__.py
sdcadmin/tests/config/test_config.py