Metadata-Version: 1.0
Name: sdcadmin
Version: 0.2
Summary: API wrapper for the SDC APIs on the admin network
Home-page: https://github.com/icclab/sdcadmin
Author: ernm
Author-email: ernm@zhaw.ch
License: Apache License, Version 2.0
Platform: UNKNOWN
